mcp_neo4j_cypher_read_only/__init__.py
mcp_neo4j_cypher_read_only/server.py
mcp_neo4j_cypher_read_only-0.1.4.dist-info/METADATA
mcp_neo4j_cypher_read_only-0.1.4.dist-info/WHEEL
mcp_neo4j_cypher_read_only-0.1.4.dist-info/entry_points.txt
mcp_neo4j_cypher_read_only-0.1.4.dist-info/RECORD
