Metadata-Version: 2.4
Name: mcp-neo4j-cypher-read-only
Version: 0.1.4
Summary: A simple Neo4j MCP server with read-only tools
Requires-Python: >=3.10
Requires-Dist: boto3>=1.28.0
Requires-Dist: mcp>=1.6.0
Requires-Dist: neo4j>=5.26.0
